odoo/addons/account_asset_transfer/README.rst
odoo/addons/account_asset_transfer/__init__.py
odoo/addons/account_asset_transfer/__manifest__.py
odoo/addons/account_asset_transfer/i18n/account_asset_transfer.pot
odoo/addons/account_asset_transfer/i18n/es.po
odoo/addons/account_asset_transfer/i18n/it.po
odoo/addons/account_asset_transfer/i18n/pt_BR.po
odoo/addons/account_asset_transfer/models/__init__.py
odoo/addons/account_asset_transfer/models/account_asset.py
odoo/addons/account_asset_transfer/models/account_asset_profile.py
odoo/addons/account_asset_transfer/readme/CONFIGURE.md
odoo/addons/account_asset_transfer/readme/CONTRIBUTORS.md
odoo/addons/account_asset_transfer/readme/DESCRIPTION.md
odoo/addons/account_asset_transfer/readme/USAGE.md
odoo/addons/account_asset_transfer/security/ir.model.access.csv
odoo/addons/account_asset_transfer/static/description/icon.png
odoo/addons/account_asset_transfer/static/description/index.html
odoo/addons/account_asset_transfer/tests/__init__.py
odoo/addons/account_asset_transfer/tests/test_account_asset_transfer.py
odoo/addons/account_asset_transfer/views/account_asset.xml
odoo/addons/account_asset_transfer/views/account_asset_profile.xml
odoo/addons/account_asset_transfer/wizard/__init__.py
odoo/addons/account_asset_transfer/wizard/account_asset_transfer.py
odoo/addons/account_asset_transfer/wizard/account_asset_transfer.xml
odoo_addon_account_asset_transfer-18.0.1.0.1.dist-info/METADATA
odoo_addon_account_asset_transfer-18.0.1.0.1.dist-info/WHEEL
odoo_addon_account_asset_transfer-18.0.1.0.1.dist-info/top_level.txt
odoo_addon_account_asset_transfer-18.0.1.0.1.dist-info/RECORD
